cloud_time_saver/__init__.py
cloud_time_saver/app/EC2create.py
cloud_time_saver/app/EC2createKP.py
cloud_time_saver/app/EC2createWithKP.py
cloud_time_saver/app/EC2deleteKP.py
cloud_time_saver/app/EC2getIDs.py
cloud_time_saver/app/EC2modifyType.py
cloud_time_saver/app/EC2restart.py
cloud_time_saver/app/EC2stop.py
cloud_time_saver/app/EC2terminate.py
cloud_time_saver/app/S3createBucket.py
cloud_time_saver/app/S3deleteBucket.py
cloud_time_saver/app/S3deleteObject.py
cloud_time_saver/app/S3deleteObjects.py
cloud_time_saver/app/S3deletePolicy.py
cloud_time_saver/app/S3downloadAllFiles.py
cloud_time_saver/app/S3downloadSingleFile.py
cloud_time_saver/app/S3listBuckets.py
cloud_time_saver/app/S3listObjects.py
cloud_time_saver/app/S3listPolicy.py
cloud_time_saver/app/S3uploadDir.py
cloud_time_saver/app/S3uploadSingleFile.py
cloud_time_saver/app/SGaddInboundRule.py
cloud_time_saver/app/SGaddOutboundRule.py
cloud_time_saver/app/SGcreate.py
cloud_time_saver/app/SGdescribeGroup.py
cloud_time_saver/app/SGgetAll.py
cloud_time_saver/app/SGremove.py
cloud_time_saver/app/SGremoveInboundRule.py
cloud_time_saver/app/SGremoveOutboundRule.py
cloud_time_saver/app/VPCcreate.py
cloud_time_saver/app/VPCdelete.py
cloud_time_saver/app/VPCdescribe.py
cloud_time_saver/app/VPCgetIDs.py
cloud_time_saver/app/__init__.py
cloud_time_saver/app/__main__.py
cloud_time_saver/app/attachEBStoEC2.py
cloud_time_saver/app/createEBS.py
cloud_time_saver/app/createEBSsnapshot.py
cloud_time_saver/app/deleteEBS.py
cloud_time_saver/app/detachEBSfromEC2.py
cloud_time_saver/app/listEBS.py
cloud_time_saver/app/main.py
cloud_time_saver/cts.py
cloud_time_saver-0.3.8.dist-info/entry_points.txt
cloud_time_saver-0.3.8.dist-info/WHEEL
cloud_time_saver-0.3.8.dist-info/METADATA
cloud_time_saver-0.3.8.dist-info/RECORD
