Metadata-Version: 2.1
Name: cloud-time-saver
Version: 0.3.8
Summary: Python CLI tool that automates working on AWS enviorment without leaving the Terminal.
Author: Marko Mandic
Author-email: mandicm223@gmail.com
Requires-Python: >=3.8,<4.0
Classifier: Programming Language :: Python :: 3
Classifier: Programming Language :: Python :: 3.10
Classifier: Programming Language :: Python :: 3.8
Classifier: Programming Language :: Python :: 3.9
Requires-Dist: boto3 (==1.19.7)
Requires-Dist: click (==8.0.3)
Requires-Dist: colorama (==0.4.4)
Requires-Dist: fire (==0.4.0)
Project-URL: repository, https://github.com/JaSamLudiMoskri/cloud_time_saver_prod
